{
    "gamertag": "The Sauce",
    "name": "Sauce",
    "featured": {
        "Eliminations - Average": "10.92",
        "Damage Done - Average": "4,261",
        "Deaths - Average": "4.85",
        "Final Blows - Average": "6.18",
        "Healing Done - Average": "1,352",
        "Objective Kills - Average": "4.54",
        "Objective Time - Average": "00:38",
        "Solo Kills - Average": "2.63"
    },
    "Combat": {
        "Eliminations": "7",
        "Final Blows": "3",
        "Shots Fired": "33",
        "Shots Hit": "8",
        "Critical Hits": "2",
        "Damage Done": "2,023",
        "Objective Kills": "5",
        "Critical Hits per Minute": "0",
        "Critical Hit Accuracy": "25%",
        "Eliminations per Life": "1",
        "Weapon Accuracy": "24%"
    },
    "Assists": {
        "Healing Done": "494",
        "Self Healing": "494"
    },
    "Best": {
        "Eliminations - Most in Life": "2",
        "Most Score within one Life": "163",
        "Damage Done - Most in Life": "724",
        "Healing Done - Most in Life": "150",
        "Kill Streak - Best": "2",
        "Damage Done - Most in Game": "1,252",
        "Healing Done - Most in Game": "256",
        "Eliminations - Most in Game": "4",
        "Final Blows - Most in Game": "2",
        "Objective Kills - Most in Game": "3",
        "Objective Time - Most in Game": "29",
        "Critical Hits - Most in Game": "2",
        "Critical Hits - Most in Life": "2",
        "Self Healing - Most in Game": "256"
    },
    "Average": {
        "Self Healing - Average": "1.34",
        "Deaths - Average": "9.55",
        "Objective Time - Average": "65.38",
        "Objective Kills - Average": "6.82",
        "Healing Done - Average": "673.47",
        "Final Blows - Average": "4.09",
        "Eliminations - Average": "9.55",
        "Damage Done - Average": "2,760.25"
    },
    "Deaths": {
        "Deaths": "7"
    },
    "Match Awards": {
        "Medals - Bronze": "2",
        "Medals - Silver": "1",
        "Medals - Gold": "1",
        "Medals": "4"
    },
    "Game": {
        "Time Played": "6 minutes",
        "Games Played": "1",
        "Score": "618",
        "Objective Time": "48"
    },
    "Miscellaneous": {
        "Offensive Assists": "7",
        "Offensive Assists - Most in Game": "2",
        "Defensive Assists": "69",
        "Defensive Assists - Most in Game": "10",
        "Healing Done": "57,055",
        "Healing Done - Average": "4,848",
        "Defensive Assists - Average": "6",
        "Offensive Assists - Average": "1"
    },
    "Hero Specific": {
        "Enemies Frozen": "4",
        "Enemies Frozen - Most in Game": "3",
        "Blizzard Kills - Most in Game": "3",
        "Blizzard Kills": "3",
        "Damage Blocked - Most in Game": "2,389",
        "Damage Blocked": "4,215",
        "Enemies Frozen - Average": "5.45",
        "Damage Blocked - Average": "5,751",
        "Blizzard Kills - Average": "4.09"
    }
}